MANIFEST.in
README.md
requirements.txt
setup.py
demo/__init__.py
demo/mnist.py
keras_drop_block/__init__.py
keras_drop_block/drop_block.py
keras_drop_block.egg-info/PKG-INFO
keras_drop_block.egg-info/SOURCES.txt
keras_drop_block.egg-info/dependency_links.txt
keras_drop_block.egg-info/top_level.txt
tests/__init__.py
tests/test_drop_block_1d.py
tests/test_drop_block_2d.py