Metadata-Version: 2.1
Name: keras-drop-block
Version: 0.7.0
Summary: DropBlock implemented in Keras
Home-page: https://github.com/CyberZHG/keras-drop-block
Author: CyberZHG
Author-email: CyberZHG@users.noreply.github.com
License: MIT
Platform: UNKNOWN
Classifier: Programming Language :: Python :: 3
Classifier: License :: OSI Approved :: MIT License
Classifier: Operating System :: OS Independent
